{
  "parent": "minecraft:recipes/root",
  "criteria": {
    "has_food": {
      "conditions": {
        "items": [
          {
            "type": "biomancy:is_food_item"
          }
        ]
      },
      "trigger": "minecraft:inventory_changed"
    },
    "has_the_recipe": {
      "conditions": {
        "recipe": "biomancy:digesting/nutrient_paste_from_digesting_excellent_food"
      },
      "trigger": "minecraft:recipe_unlocked"
    }
  },
  "requirements": [
    [
      "has_food",
      "has_the_recipe"
    ]
  ],
  "rewards": {
    "recipes": [
      "biomancy:digesting/nutrient_paste_from_digesting_excellent_food"
    ]
  },
  "sends_telemetry_event": false
}