{
  "advancements": [
    {
      "advancement": {
        "parent": "minecraft:recipes/root",
        "criteria": {
          "has_pewen_sap": {
            "conditions": {
              "items": [
                {
                  "items": [
                    "alexscaves:pewen_sap"
                  ]
                }
              ]
            },
            "trigger": "minecraft:inventory_changed"
          },
          "has_the_recipe": {
            "conditions": {
              "recipe": "biomancy:decomposing/pewen_sap_decomposing"
            },
            "trigger": "minecraft:recipe_unlocked"
          }
        },
        "requirements": [
          [
            "has_pewen_sap",
            "has_the_recipe"
          ]
        ],
        "rewards": {
          "recipes": [
            "biomancy:decomposing/pewen_sap_decomposing"
          ]
        },
        "sends_telemetry_event": false
      },
      "conditions": [
        {
          "type": "forge:mod_loaded",
          "modid": "alexscaves"
        }
      ]
    }
  ]
}