{
  "type": "biomancy:decomposing",
  "input": {
    "ingredient": {
      "item": "minecraft:player_head"
    },
    "count": 1
  },
  "outputs": [
    {
      "result": {
        "item": "biomancy:flesh_bits",
        "count_range": {
          "type": "uniform",
          "min": 19,
          "max": 32
        }
      }
    },
    {
      "result": {
        "item": "biomancy:elastic_fibers",
        "count_range": {
          "type": "uniform",
          "min": 5,
          "max": 9
        }
      }
    },
    {
      "result": {
        "item": "minecraft:skeleton_skull",
        "count_range": {
          "type": "constant",
          "value": 1
        }
      }
    }
  ],
  "time": 686
}