{
  "parent": "minecraft:recipes/root",
  "rewards": {
    "recipes": [
      "biomancy:red_sand_from_oxides"
    ]
  },
  "criteria": {
    "has_oxides": {
      "trigger": "minecraft:inventory_changed",
      "conditions": {
        "items": [
          {
            "items": [
              "biomancy:oxides"
            ]
          }
        ]
      }
    },
    "has_the_recipe": {
      "trigger": "minecraft:recipe_unlocked",
      "conditions": {
        "recipe": "biomancy:red_sand_from_oxides"
      }
    }
  },
  "requirements": [
    [
      "has_oxides",
      "has_the_recipe"
    ]
  ]
}