{
  "type": "biomancy:decomposing",
  "conditions": [
    {
      "type": "forge:mod_loaded",
      "modid": "alexscaves"
    }
  ],
  "ingredient": {
    "item": "alexscaves:curly_fern"
  },
  "nutrientsCost": 1,
  "processingTime": 120,
  "results": [
    {
      "countRange": {
        "type": "uniform",
        "max": 4,
        "min": 2
      },
      "item": "biomancy:organic_matter"
    },
    {
      "countRange": {
        "type": "uniform",
        "max": 2,
        "min": 1
      },
      "item": "minecraft:lime_dye"
    }
  ]
}